mt940/MT940-optional.txt
mt940/MT940.txt
mt940/__init__.py
mt940/__init__.py.bak
mt940/test.py
mt940-0.6.0.dist-info/METADATA
mt940-0.6.0.dist-info/WHEEL
mt940-0.6.0.dist-info/top_level.txt
mt940-0.6.0.dist-info/RECORD
